coderedcms/__init__.py
coderedcms/admin_urls.py
coderedcms/apps.py
coderedcms/fields.py
coderedcms/forms.py
coderedcms/importexport.py
coderedcms/recaptcha.py
coderedcms/search_urls.py
coderedcms/settings.py
coderedcms/urls.py
coderedcms/utils.py
coderedcms/views.py
coderedcms/wagtail_hooks.py
coderedcms/widgets.py
coderedcms/api/mailchimp.py
coderedcms/bin/__init__.py
coderedcms/bin/coderedcms.py
coderedcms/blocks/__init__.py
coderedcms/blocks/base_blocks.py
coderedcms/blocks/content_blocks.py
coderedcms/blocks/html_blocks.py
coderedcms/blocks/layout_blocks.py
coderedcms/blocks/stream_form_blocks.py
coderedcms/blocks/tests/__init__.py
coderedcms/blocks/tests/test_blocks.py
coderedcms/migrations/0001_initial.py
coderedcms/migrations/0002_auto_20180829_1538.py
coderedcms/migrations/0003_auto_20180912_1632.py
coderedcms/migrations/0004_auto_20181119_1507.py
coderedcms/migrations/0005_auto_20181214_2214.py
coderedcms/migrations/0006_mailchimpapisettings.py
coderedcms/migrations/0007_auto_20190114_1515.py
coderedcms/migrations/0008_auto_20190122_1242.py
coderedcms/migrations/0009_auto_20190201_1546.py
coderedcms/migrations/0010_auto_20190320_1231.py
coderedcms/migrations/0010_generalsettings_email.py
coderedcms/migrations/0010_remove_generalsettings_robots.py
coderedcms/migrations/0011_merge_20190322_1309.py
coderedcms/migrations/0012_merge_20190322_1324.py
coderedcms/migrations/0013_pagepreview_templates.py
coderedcms/migrations/0014_classifiers.py
coderedcms/migrations/0015_coderedsessionformsubmission_coderedsubmissionrevision.py
coderedcms/migrations/0016_auto_20191025_1620.py
coderedcms/migrations/0017_generalsettings_external_new_tab.py
coderedcms/migrations/0018_auto_20200805_1702.py
coderedcms/migrations/0019_spelling_corrections.py
coderedcms/migrations/0020_auto_20210527_1030.py
coderedcms/migrations/0021_auto_20210730_1637.py
coderedcms/migrations/0022_auto_20210731_1853.py
coderedcms/migrations/0023_auto_20210908_1702.py
coderedcms-6.0.0.dist-info/licenses/LICENSE.txt
coderedcms-6.0.0.dist-info/METADATA
coderedcms-6.0.0.dist-info/WHEEL
coderedcms-6.0.0.dist-info/entry_points.txt
coderedcms-6.0.0.dist-info/top_level.txt
coderedcms-6.0.0.dist-info/RECORD
