Metadata-Version: 2.4
Name: coderedcms
Version: 6.0.0
Summary: Wagtail + CodeRed Extensions enabling rapid development of marketing-focused websites.
Author-email: CodeRed LLC <info@coderedcorp.com>
License: Copyright (c) CodeRed LLC and individual contributors.
Project-URL: Source, https://github.com/coderedcorp/coderedcms
Project-URL: Documentation, https://docs.coderedcorp.com/wagtail-crx/
Project-URL: Changelog, https://docs.coderedcorp.com/wagtail-crx/releases/
Classifier: Environment :: Web Environment
Classifier: Framework :: Django
Classifier: Intended Audience :: Developers
Classifier: Operating System :: OS Independent
Classifier: Programming Language :: Python
Classifier: Programming Language :: Python :: 3
Classifier: Programming Language :: Python :: 3.10
Classifier: Programming Language :: Python :: 3.11
Classifier: Programming Language :: Python :: 3.12
Classifier: Programming Language :: Python :: 3.13
Classifier: Programming Language :: Python :: 3 :: Only
Classifier: Framework :: Django
Classifier: Framework :: Django :: 4.2
Classifier: Framework :: Django :: 5.0
Classifier: Framework :: Django :: 5.1
Classifier: Framework :: Django :: 5.2
Classifier: Framework :: Wagtail
Classifier: Framework :: Wagtail :: 7
Classifier: Topic :: Internet :: WWW/HTTP
Classifier: Topic :: Internet :: WWW/HTTP :: Dynamic Content
Classifier: Topic :: Internet :: WWW/HTTP :: Site Management
Requires-Python: >=3.10
License-File: LICENSE.txt
Requires-Dist: beautifulsoup4<5,>=4.8
Requires-Dist: django-eventtools==1.0.*
Requires-Dist: django-bootstrap5==25.2
Requires-Dist: Django<6.0,>=4.2
Requires-Dist: geocoder==1.38.*
Requires-Dist: icalendar==6.3.*
Requires-Dist: wagtail<8.0,>=7.0
Requires-Dist: wagtail-cache==3.*
Requires-Dist: wagtail-flexible-forms<3.0,>=2.1
Requires-Dist: wagtail-seo<4.0,>=3.1
Dynamic: license-file
